monolith/__init__.py
monolith/dynamics.cpython-312-x86_64-linux-gnu.so
monolith/dynamics.pyi
monolith/dynamics_dep/__init__.py
monolith/dynamics_dep/drag.py
monolith/dynamics_dep/j2.py
monolith/dynamics_dep/j3.py
monolith/dynamics_dep/manuevers.py
monolith/dynamics_dep/srp.py
monolith/dynamics_dep/three_body.py
monolith/dynamics_dep/two_body.py
monolith/environment/__init__.py
monolith/ode/__init__.py
monolith/ode/ode87.py
monolith/planets.cpython-312-x86_64-linux-gnu.so
monolith/planets.pyi
monolith/states/__init__.py
monolith/utils/__init__.py
monolith_space-0.1.1.dist-info/METADATA
monolith_space-0.1.1.dist-info/WHEEL
monolith_space-0.1.1.dist-info/RECORD
