Metadata-Version: 2.3
Name: monolith-space
Version: 0.1.1
Summary: Orbital Mechanics library
Author: Aaron Berkhoff
Author-email: aaronberkhoff@outlook.com
Requires-Python: >=3.12,<4.0
Classifier: Programming Language :: Python :: 3
Classifier: Programming Language :: Python :: 3.12
Classifier: Programming Language :: Python :: 3.13
Provides-Extra: dev
Requires-Dist: mypy (>=1.16.0,<2.0.0) ; extra == "dev"
Requires-Dist: numpy (>=2.2.6,<3.0.0)
Requires-Dist: pybind11 (>=2.11.0,<3.0.0) ; extra == "dev"
Requires-Dist: pybind11-stubgen (>=2.5.5,<3.0.0) ; extra == "dev"
